featurefactory/__init__.py
featurefactory/_modidx.py
featurefactory/core.py
featurefactory-0.0.1.dist-info/LICENSE
featurefactory-0.0.1.dist-info/METADATA
featurefactory-0.0.1.dist-info/WHEEL
featurefactory-0.0.1.dist-info/entry_points.txt
featurefactory-0.0.1.dist-info/top_level.txt
featurefactory-0.0.1.dist-info/RECORD
